stistools/__init__.py
stistools/add_stis_s_region.py
stistools/basic2d.py
stistools/calstis.py
stistools/crrej_from_raw.py
stistools/ctestis.py
stistools/doppinfo.py
stistools/evaldisp.py
stistools/gettable.py
stistools/inttag.py
stistools/mktrace.py
stistools/observation.py
stistools/ocrreject.py
stistools/ocrreject_exam.py
stistools/orbit.py
stistools/poisson_err.py
stistools/r_util.py
stistools/radialvel.py
stistools/sshift.py
stistools/stisnoise.py
stistools/tastis.py
stistools/version.py
stistools/wavecal.py
stistools/wavelen.py
stistools/wx2d.py
stistools/x1d.py
stistools/x2d.py
stistools/defringe/__init__.py
stistools/defringe/_findloc.py
stistools/defringe/_fit1d.py
stistools/defringe/_response.py
stistools/defringe/defringe.py
stistools/defringe/mkfringeflat.py
stistools/defringe/normspflat.py
stistools/defringe/prepspec.py
stistools/pars/basic2d.cfg
stistools/pars/basic2d.cfgspc
stistools/pars/calstis.cfg
stistools/pars/calstis.cfgspc
stistools/pars/ocrreject.cfg
stistools/pars/ocrreject.cfgspc
stistools/pars/wavecal.cfg
stistools/pars/wavecal.cfgspc
stistools/pars/x1d.cfg
stistools/pars/x1d.cfgspc
stistools/pars/x2d.cfg
stistools/pars/x2d.cfgspc
stistools-1.4.6.dist-info/licenses/LICENSE.txt
tests/Test_x1d.py
tests/__init__.py
tests/resources.py
tests/test_basic2d.py
tests/test_calstis.py
tests/test_crrej_from_raw.py
tests/test_ctestis.py
tests/test_defringe.py
tests/test_doppinfo.py
tests/test_inttag.py
tests/test_mktrace.py
tests/test_ocrreject.py
tests/test_ocrreject_exam.py
tests/test_poisson_err.py
tests/test_stisnoise.py
tests/test_tastis.py
tests/test_wx2d.py
tests/helpers/__init__.py
tests/helpers/io.py
tests/helpers/utils.py
stistools-1.4.6.dist-info/METADATA
stistools-1.4.6.dist-info/WHEEL
stistools-1.4.6.dist-info/entry_points.txt
stistools-1.4.6.dist-info/top_level.txt
stistools-1.4.6.dist-info/RECORD
