Metadata-Version: 2.4
Name: stistools
Version: 1.4.6
Summary: Tools for STIS (Space Telescope Imaging Spectrograph)
Author: Paul Barrett, Phil Hodge
Classifier: Intended Audience :: Science/Research
Classifier: Operating System :: OS Independent
Classifier: Programming Language :: Python
Classifier: Topic :: Scientific/Engineering :: Astronomy
Classifier: Topic :: Software Development :: Libraries :: Python Modules
Requires-Python: >=3.10
License-File: LICENSE.txt
Requires-Dist: astropy>=5.1
Requires-Dist: numpy
Requires-Dist: scipy
Requires-Dist: stsci.tools
Requires-Dist: pysiaf
Requires-Dist: astroquery
Requires-Dist: matplotlib>=3.5
Provides-Extra: test
Requires-Dist: pytest; extra == "test"
Requires-Dist: ci-watson>=0.8.0; extra == "test"
Provides-Extra: docs
Requires-Dist: ipython; extra == "docs"
Requires-Dist: sphinx; extra == "docs"
Requires-Dist: stsci_rtd_theme; extra == "docs"
Requires-Dist: sphinx_automodapi; extra == "docs"
Requires-Dist: numpydoc; extra == "docs"
Dynamic: license-file
